stxdefender.py
stxdefender-1.0.4.dist-info/licenses/LICENSE
stxdefender-1.0.4.dist-info/METADATA
stxdefender-1.0.4.dist-info/WHEEL
stxdefender-1.0.4.dist-info/entry_points.txt
stxdefender-1.0.4.dist-info/top_level.txt
stxdefender-1.0.4.dist-info/RECORD
