Metadata-Version: 2.4
Name: stxdefender
Version: 1.0.4
Summary: Python Source Code Encryption Tool - Enterprise-grade protection for your Python source code
Home-page: https://github.com/iukdma/stxdefender
Author: STXDefender Team
Author-email: support@stxdefender.example.com
Project-URL: Bug Reports, https://github.com/iukdma/stxdefender/issues
Project-URL: Source, https://github.com/iukdma/stxdefender
Project-URL: Documentation, https://github.com/iukdma/stxdefender#readme
Keywords: encryption,python,source code protection,obfuscation,security
Classifier: Development Status :: 4 - Beta
Classifier: Intended Audience :: Developers
Classifier: License :: OSI Approved :: MIT License
Classifier: Operating System :: OS Independent
Classifier: Programming Language :: Python :: 3
Classifier: Programming Language :: Python :: 3.8
Classifier: Programming Language :: Python :: 3.9
Classifier: Programming Language :: Python :: 3.10
Classifier: Programming Language :: Python :: 3.11
Classifier: Programming Language :: Python :: 3.12
Classifier: Topic :: Software Development :: Libraries :: Python Modules
Classifier: Topic :: Security :: Cryptography
Requires-Python: >=3.8
License-File: LICENSE
Requires-Dist: cryptography>=41.0.0
Requires-Dist: requests>=2.31.0
Dynamic: author
Dynamic: author-email
Dynamic: classifier
Dynamic: description
Dynamic: description-content-type
Dynamic: home-page
Dynamic: keywords
Dynamic: license-file
Dynamic: project-url
Dynamic: requires-dist
Dynamic: requires-python
Dynamic: summary
